setup.py
distributions_sumit/Binomialdistribution.py
distributions_sumit/Gaussiandistribution.py
distributions_sumit/Generaldistribution.py
distributions_sumit/__init__.py
distributions_sumit.egg-info/PKG-INFO
distributions_sumit.egg-info/SOURCES.txt
distributions_sumit.egg-info/dependency_links.txt
distributions_sumit.egg-info/not-zip-safe
distributions_sumit.egg-info/top_level.txt