Metadata-Version: 2.1
Name: distributions-sumit
Version: 0.1
Summary: Gaussian distributions and Binomial distributions
Author: Sumit Kumar
Author-email: sumitkrkanti@gmail.com
